datatrove/__init__.py
datatrove/data.py
datatrove/io.py
datatrove/assets/banned_subwords.txt
datatrove/assets/banned_words.txt
datatrove/assets/soft_banned_words.txt
datatrove/assets/url_filterblacklists.tar.gz
datatrove/executor/__init__.py
datatrove/executor/base.py
datatrove/executor/local.py
datatrove/executor/slurm.py
datatrove/pipeline/__init__.py
datatrove/pipeline/base.py
datatrove/pipeline/dedup/__init__.py
datatrove/pipeline/dedup/bloom_filter.py
datatrove/pipeline/dedup/exact_substrings.py
datatrove/pipeline/dedup/minhash.py
datatrove/pipeline/dedup/sentence_dedup.py
datatrove/pipeline/dedup/url_dedup.py
datatrove/pipeline/extractors/__init__.py
datatrove/pipeline/extractors/base.py
datatrove/pipeline/extractors/modular.py
datatrove/pipeline/extractors/trafilatura.py
datatrove/pipeline/filters/__init__.py
datatrove/pipeline/filters/base_filter.py
datatrove/pipeline/filters/c4_quality_filter.py
datatrove/pipeline/filters/fasttext_filter.py
datatrove/pipeline/filters/fineweb_quality_filter.py
datatrove/pipeline/filters/gopher_quality_filter.py
datatrove/pipeline/filters/gopher_repetition_filter.py
datatrove/pipeline/filters/lambda_filter.py
datatrove/pipeline/filters/language_filter.py
datatrove/pipeline/filters/regex_filter.py
datatrove/pipeline/filters/sampler_filter.py
datatrove/pipeline/filters/unigram_log_probs.py
datatrove/pipeline/filters/url_filter.py
datatrove/pipeline/formatters/__init__.py
datatrove/pipeline/formatters/base.py
datatrove/pipeline/formatters/ftfy.py
datatrove/pipeline/formatters/pii.py
datatrove/pipeline/formatters/symbol_lines_remover.py
datatrove/pipeline/readers/__init__.py
datatrove/pipeline/readers/base.py
datatrove/pipeline/readers/csv.py
datatrove/pipeline/readers/huggingface.py
datatrove/pipeline/readers/ipc.py
datatrove/pipeline/readers/jsonl.py
datatrove/pipeline/readers/parquet.py
datatrove/pipeline/readers/warc.py
datatrove/pipeline/stats/__init__.py
datatrove/pipeline/stats/doc_len.py
datatrove/pipeline/stats/urls.py
testing_datatrove-513211.0.1.dist-info/LICENSE
testing_datatrove-513211.0.1.dist-info/METADATA
testing_datatrove-513211.0.1.dist-info/WHEEL
testing_datatrove-513211.0.1.dist-info/entry_points.txt
testing_datatrove-513211.0.1.dist-info/top_level.txt
testing_datatrove-513211.0.1.dist-info/RECORD
