Metadata-Version: 2.1
Name: testing-datatrove
Version: 513211.0.1
Summary: HuggingFace library to process and filter large amounts of webdata
Author-email: "HuggingFace Inc." <guilherme@huggingface.co>
License: Apache-2.0
Project-URL: Repository, https://github.com/huggingface/datatrove
Keywords: data,machine,learning,processing
Classifier: Intended Audience :: Developers
Classifier: Intended Audience :: Education
Classifier: Intended Audience :: Science/Research
Classifier: License :: OSI Approved :: Apache Software License
Classifier: Operating System :: OS Independent
Classifier: Programming Language :: Python :: 3
Classifier: Programming Language :: Python :: 3.10
Classifier: Programming Language :: Python :: 3.11
Classifier: Programming Language :: Python :: 3.12
Classifier: Topic :: Scientific/Engineering :: Artificial Intelligence
Requires-Python: >=3.10.0
License-File: LICENSE
Requires-Dist: dill >=0.3.0
Requires-Dist: fsspec >=2023.12.2
Requires-Dist: huggingface-hub >=0.17.0
Requires-Dist: humanize
Requires-Dist: loguru >=0.7.0
Requires-Dist: multiprocess
Requires-Dist: numpy >=1.25.0
Requires-Dist: tqdm
Provides-Extra: all
Requires-Dist: testing-datatrove[quality] ; extra == 'all'
Requires-Dist: testing-datatrove[testing] ; extra == 'all'
Provides-Extra: cli
Requires-Dist: rich ; extra == 'cli'
Provides-Extra: dev
Requires-Dist: testing-datatrove[all] ; extra == 'dev'
Provides-Extra: io
Requires-Dist: faust-cchardet ; extra == 'io'
Requires-Dist: pyarrow ; extra == 'io'
Requires-Dist: python-magic ; extra == 'io'
Requires-Dist: warcio ; extra == 'io'
Requires-Dist: datasets >=2.18.0 ; extra == 'io'
Provides-Extra: processing
Requires-Dist: fasttext-wheel ; extra == 'processing'
Requires-Dist: nltk ; extra == 'processing'
Requires-Dist: inscriptis ; extra == 'processing'
Requires-Dist: tldextract ; extra == 'processing'
Requires-Dist: trafilatura >=1.8.0 ; extra == 'processing'
Requires-Dist: tokenizers ; extra == 'processing'
Requires-Dist: ftfy ; extra == 'processing'
Requires-Dist: fasteners ; extra == 'processing'
Requires-Dist: xxhash ; extra == 'processing'
Provides-Extra: quality
Requires-Dist: ruff >=0.1.5 ; extra == 'quality'
Provides-Extra: s3
Requires-Dist: s3fs >=2023.12.2 ; extra == 's3'
Provides-Extra: testing
Requires-Dist: testing-datatrove[cli] ; extra == 'testing'
Requires-Dist: testing-datatrove[io] ; extra == 'testing'
Requires-Dist: testing-datatrove[processing] ; extra == 'testing'
Requires-Dist: testing-datatrove[s3] ; extra == 'testing'
Requires-Dist: pytest ; extra == 'testing'
Requires-Dist: pytest-timeout ; extra == 'testing'
Requires-Dist: pytest-xdist ; extra == 'testing'
Requires-Dist: moto[s3,server] ; extra == 'testing'
